{"hate": {"10": ["south", "korean"], "1": ["show", "school", "lawrence", "mum", "water", "dry", "sign", "empty", "phone", "me", "room", "cam", "drink", "peanuts", "homework", "mom", "dad", "alcohol", "question", "feud"], "0": ["saying", "ugh", "skin", "pretty", "hope", "worse", "stop", "cook", "level", "fear", "body", "lotion", "great", "career", "thinking", "amount", "semester", "next", "much", "tell", "sharing", "baby", "holocaust", "making", "heart", "trump", "sleeping", "fart", "denial", "break", "tho", "dream", "move", "awful", "thanks", "still", "crying", "possible", "know", "hands", "loss", "cool", "em", "right", "back", "year", "cough", "super", "care", "jumping", "act", "think", "feet", "fast", "realization", "head", "cats", "haven", "he", "wish", "mind", "microphone", "aside", "take", "nice", "log", "rule", "face", "pattern"], "3": ["four", "therapist", "michigan", "fan", "team", "husband", "view", "fans", "job", "montreal", "learn", "middle", "embrace", "end", "shirt", "shit", "alabama", "side", "soccer", "basketball", "divorce", "there", "final", "marriage", "constant", "tide", "film", "star", "football", "don", "wife"], "2": ["battle", "enough", "words", "alexander", "population", "see", "giving", "laugh", "use", "talent", "lock", "hoe", "wrong", "money", "paper", "character", "real", "dark", "always", "madrid", "ass", "reason", "blind", "feel", "bitch", "way", "matter", "say", "general", "no", "nothing", "stupid"], "5": ["meditation", "means", "small", "round", "rite", "death", "fake", "eye", "life", "tiger", "need", "third", "talk", "cause", "violence", "aliens", "sex"], "4": ["radio", "iran", "iraq", "shuffle", "hour", "song", "till", "camera", "dancing", "playing", "format", "schedule", "days", "stand", "syria", "listen", "new_song", "up", "play", "repeat", "ghost"], "7": ["hate", "going", "fall", "sleep", "waking", "let", "coma", "kitchen", "last", "wake", "director", "date", "better", "nose", "grub", "hibernate", "wake_up", "night", "joseph", "frost", "sore", "bed", "feeling", "minutes", "throat", "hangover", "nap", "sick"], "6": ["boyfriend", "die", "criminal", "misanthrope", "if", "man", "kill", "cold", "scorpio", "ducking", "people", "re", "turn", "wrath", "relationship", "fact"], "9": ["mosque", "black", "bag", "stuff", "bail", "muslim", "address", "patience", "belt", "two", "checkout", "fire", "clue", "cunt", "car", "give", "mess", "rapid", "group", "wee", "orange", "hall", "lost", "gender", "found", "dead", "girl", "race", "power", "ate", "number", "due", "female", "open", "city", "ordering", "system", "part", "line", "single", "alarm", "dog"], "8": ["cannabis", "morning", "bad", "knowing", "experience", "whole", "damn", "shopping", "thing", "things", "user", "bunch", "source", "swastika", "jesus", "god", "store", "grocery", "marijuana", "thought", "america", "mood"]}}