{"beauty": {"1": ["queen", "sage", "cincinnati", "jaguar", "qi", "spotter", "fetish", "tortoise", "highland", "lagos", "polo", "palace", "dior", "oh", "bennett", "kenya", "seattle", "tao", "guru", "peoples", "countryside", "tho", "indigo", "edmonton", "glen", "samba", "bowie", "republic", "maya", "ya", "hunter", "norfolk", "masters", "clown", "ea", "peter", "snail", "god", "columbus", "david", "stuart", "essex", "master", "cornwall", "bud", "ben", "bell", "angel", "dallas", "cave", "baker", "mrs", "moonlight"], "0": ["shot", "sleep", "threshold", "tickle", "going", "pretty", "express", "blast", "morning", "race", "set", "second", "wow", "finger", "approach", "attention", "whoop", "let", "change", "ramp", "job", "bow", "mentor", "giveaway", "mobility", "height", "use", "eye", "two", "much", "call", "tell", "stick", "chatter", "case", "topic", "none", "look", "solid", "straight", "praise", "growing", "high", "triple", "chase", "goal", "things", "may", "whole", "counter", "contact", "thanks", "touch", "splurge", "danger", "better", "absence", "crying", "combination", "know", "sensational", "loss", "blemish", "found", "deal", "back", "frequency", "mirror", "witness", "looking", "health", "cause", "peek", "hibernate", "monster", "power", "care", "feel", "radical", "miss", "stare", "guess", "bite", "fight", "head", "butt", "true", "zero", "feeling", "feet", "eyes", "slap", "at", "need", "face", "beyond", "latter", "take", "pain", "falls", "vice", "cover", "professional"], "3": ["personality", "courage", "vision", "palette", "darkness", "nature", "importance", "sorrow", "femininity", "expression", "landscape", "insecurity", "spirit", "beautiful", "bittersweet", "aesthetics", "purity", "pure", "designer", "beauty", "longing", "natural", "vintage", "hearts", "sky", "dark", "gift", "heart", "superiority", "freshness", "stardust", "architecture", "innocence", "ache", "faith", "gusto", "beacon", "glow", "grace", "spice", "heartstrings", "duet", "fashion", "imagination"], "2": ["gold", "tequila", "zinc", "skin", "carpet", "chain", "scooter", "technique", "sulfate", "removal", "black", "brown", "premium", "trees", "closeup", "rover", "aluminum", "commons", "magnet", "whitening", "portable", "smooth", "bedroom", "blue", "pedicure", "makeup", "water", "tub", "cup", "massage", "acne", "oregano", "cent", "company", "mine", "barrette", "pack", "transponder", "liter", "conditioner", "tattoo", "pan", "balm", "lab", "kit", "waterfall", "cleaning", "liquid", "liner", "bangle", "facial", "bracelet", "square", "hair", "flower", "purple", "nib", "red", "pendant", "keratin", "organic", "package", "filter", "retail", "float", "bath", "cocoa", "wash", "brush", "cafeteria", "aromatherapy", "caviar", "paint", "moisture", "potato", "shampoo", "bed", "fingering", "coconut", "curl", "mint", "cream", "soak", "parks", "equipment", "lip", "oil", "matrix", "lipstick", "oral", "rinse"], "4": ["woman", "she", "baby", "wheelchair", "girl", "female", "mother"]}}