{"commerce": {"1": ["coach", "month", "hanging", "pause", "charge", "worst", "boot", "level", "bad", "math", "round", "force", "surgery", "showcase", "ways", "opening", "job", "change", "convert", "whole", "point", "cosmetic", "visit", "two", "next", "much", "treat", "hawking", "meeting", "more", "great", "must", "main", "look", "equation", "will", "can", "making", "guide", "history", "give", "eve", "high", "ready", "travel", "trip", "register", "position", "help", "better", "save", "might", "big", "know", "now", "shoulder", "success", "herald", "series", "connect", "lead", "re", "who", "free", "post", "stage", "days", "keep", "place", "road", "meet", "open", "top", "start", "low", "head", "part", "gain", "line", "elite", "he", "see", "matter", "care", "runner", "pro", "at", "check", "take", "nice", "begin", "star", "football", "camp", "cover", "senior"], "0": ["shop", "bedside", "bail", "case", "gender", "gun", "bag", "disaster", "refugee", "darkness", "box", "restaurant", "exploitation", "trial", "army", "door", "facade", "organizer", "party", "law", "capitalist", "vintage", "office", "police", "wall", "toiletry", "hall", "rumor", "brutality", "equality", "postcard", "amnesty", "container", "card", "consumerism", "modernity", "story", "script", "escort", "war", "cabinet", "wardrobe", "genealogy", "stories", "piece", "ship", "mountain", "self", "book", "town", "assault", "wife", "dog"], "3": ["population", "executive", "premium", "rise", "maritime", "large", "small", "cash", "rate", "invention", "expert", "review", "public", "specialist", "keynote", "address", "news", "lawsuit", "forum", "social", "use", "insider", "manufacturer", "firm", "company", "award", "customer", "commerce", "account", "share", "patent", "media", "strategy", "stock", "development", "plans", "automation", "director", "data", "builder", "banks", "order", "latest", "money", "insight", "supply", "labor", "advertising", "seeking", "bid", "world", "tourism", "generation", "group", "insurance", "hacker", "banking", "profit", "convenience", "research", "content", "internet", "business", "marketing", "million", "release", "retail", "software", "number", "channels", "entrepreneur", "service", "relations", "rates", "buy", "purchase", "buying", "vice", "participation", "marketplace", "partnership", "stake", "storage", "update", "services", "mobile", "industry", "daily", "subscription", "directory", "consumer"], "2": ["san_francisco", "text", "turkish", "paris", "folks", "boyle", "michael", "bay", "sea", "click", "israeli", "muslim", "french", "franklin", "bristol", "via", "egypt", "wit", "ma", "worm", "indie", "species", "louisville", "kurdish", "chapman", "st", "birmingham", "thanks", "bowie", "stephen", "texas", "february", "name", "miami", "habitat", "red", "benjamin", "york", "english", "jerusalem", "arlington", "philadelphia", "nigeria", "albert", "isis", "uk", "ana", "chat", "dallas", "phoenix", "spencer", "vietnam"]}}