{"committee": {"1": ["selection", "month", "four", "decade", "slot", "ballet", "sent", "hit", "beat", "berth", "session", "team", "round", "set", "ten", "past", "best", "million", "hero", "opening", "meet", "hours", "career", "games", "pick", "action", "win", "football", "semester", "visit", "two", "next", "stage", "today", "present", "making", "history", "eve", "high", "bowl", "running", "date", "single", "position", "playing", "latest", "beloved", "suspension", "soccer", "excited", "bid", "invitation", "game", "half", "front", "lost", "rock", "back", "opener", "roundup", "days", "place", "due", "swing", "first", "three", "playoff", "open", "basketball", "twenty", "top", "least", "start", "forward", "head", "form", "cup", "part", "atom", "line", "final", "fans", "supremo", "tonight", "at", "season", "championship", "star", "reach", "together"], "0": ["saying", "lack", "follow", "hate", "young", "sitting", "words", "bad", "guy", "sabotage", "we", "let", "come", "change", "great", "whole", "use", "much", "call", "more", "warm", "claim", "trump", "give", "if", "drink", "guys", "maybe", "counter", "thought", "keeping", "kill", "still", "better", "might", "then", "sooner", "know", "truth", "right", "looking", "cause", "ask", "everyone", "there", "he", "kind", "problem", "say", "who", "nothing", "why", "happening"], "3": ["advisory", "planning", "staff", "terror", "rescue", "joint", "report", "commons", "force", "quake", "national", "culture", "college", "laureate", "state", "capital", "public", "water", "job", "news", "debt", "forum", "region", "economics", "workplace", "duty", "family", "anti", "trust", "targeting", "working", "poet", "meeting", "fire", "gas", "search", "child", "account", "bill", "engineering", "advocacy", "terrorist", "court", "grant", "travel", "government", "cardinal", "endorsement", "party", "oil", "loyalty", "bullying", "student", "president", "law", "relief", "money", "laptop", "committee", "police", "writing", "farmer", "paramilitary", "officer", "regulation", "gun", "aids", "large", "research", "health", "electronics", "agreement", "pressure", "panel", "refugee", "radical", "image", "safety", "message", "disaster", "district", "system", "attack", "war", "youth", "care", "life", "general", "plan", "education", "campus", "corporation", "self", "peace", "book", "assist", "shelter", "collaboration", "work", "consumer"], "2": ["german", "thursday", "lord", "michigan", "philippines", "reid", "ohio", "milo", "iran", "indian", "muslim", "pakistan", "via", "minnesota", "israel", "word", "libya", "india", "spelling", "london", "st", "nancy", "alabama", "thanks", "japan", "bowie", "ops", "world", "january", "twitter", "qatar", "nepal", "arizona", "friday", "charleston", "clinton", "damn", "hillary", "andy", "checkout", "un", "russia", "pro", "allen", "pelosi"]}}