{"dallas": {"1": ["coach", "month", "four", "title", "hit", "beat", "fan", "sleeve", "morning", "team", "national", "past", "missing", "closed", "international", "opening", "meet", "news", "last", "games", "fans", "jersey", "win", "two", "today", "history", "eve", "high", "middle", "shirt", "bowl", "skater", "helmet", "yesterday", "alert", "date", "president", "winter", "enter", "playing", "left", "rose", "winning", "bid", "practice", "break", "game", "half", "night", "series", "lead", "re", "dating", "associate", "marketing", "free", "card", "days", "place", "first", "due", "playoff", "open", "basketball", "final", "head", "season", "brand", "line", "second", "record", "classic", "pro", "year", "tonight", "at", "play", "championship", "star", "slump", "football", "contest", "vice", "bracket", "apparel", "fresh", "latest"], "0": ["maine", "dick", "minnesota", "black", "obama", "michigan", "louis", "blue", "chicago", "christian", "april", "rodgers", "via", "madness", "africa", "ether", "bliss", "dior", "atlanta", "mexico", "december", "vs", "id", "pink", "nike", "sunday", "blair", "hawk", "thai", "st", "alabama", "houston", "warren", "bowie", "texas", "lambert", "january", "england", "oklahoma", "daniel", "dutch", "red", "friday", "york", "david", "american", "raleigh", "austin", "washington", "hawks", "tom", "john", "dallas", "monday", "jones"], "3": ["catch", "going", "pretty", "worth", "watch", "kind", "difference", "cool", "large", "bad", "guy", "see", "are", "best", "sum", "job", "let", "come", "change", "great", "experience", "buzz", "whole", "point", "use", "give", "much", "more", "keeping", "wild", "making", "control", "crazy", "want", "huge", "things", "moment", "no", "thought", "money", "move", "thanks", "amazing", "better", "might", "know", "now", "found", "luck", "right", "deal", "statistic", "looking", "forth", "power", "care", "wrong", "turn", "think", "there", "size", "fight", "wonderful", "happy", "enough", "part", "he", "pull", "inside", "slap", "need", "self", "take", "absurd", "fact"], "2": ["show", "radio", "earth", "northern", "trees", "ticket", "celebrate", "school", "leather", "gun", "river", "art", "concert", "street", "video", "movie", "state", "water", "restaurant", "airport", "highland", "family", "village", "west", "live", "music", "stadium", "life", "circus", "shopping", "fire", "company", "wheeler", "adult", "baby", "commerce", "room", "car", "air", "indie", "dinner", "fame", "party", "designer", "beauty", "premiere", "lighting", "authentic", "theater", "savings", "south", "police", "sky", "march", "lunch", "hall", "postcard", "choir", "group", "lobster", "home", "girl", "ice", "eating", "shipping", "retail", "road", "facility", "city", "north", "park", "grocery", "planet", "flight", "breakfast", "education", "trip", "book", "foundry"]}}