{"double": {"1": ["battle", "rough", "headliner", "fifth", "impact", "taps", "bust", "charge", "pride", "digit", "worse", "watch", "coast", "toss", "eve", "bad", "team", "doubles", "round", "set", "pass", "wonder", "clock", "giving", "score", "great", "action", "vault", "extra", "win", "header", "negative", "much", "line", "landed", "warm", "chianti", "will", "cast", "era", "proof", "tap", "trump", "give", "high", "numbers", "triple", "stole", "string", "winter", "guarantee", "economy", "sterling", "date", "stack", "counter", "responsibility", "playing", "wind", "money", "move", "still", "blow", "group", "coaching", "bloc", "match", "couple", "spell", "five", "know", "half", "front", "now", "success", "victory", "everyone", "back", "competition", "obsession", "stud", "turning", "million", "care", "training", "place", "act", "scare", "block", "anointing", "two", "rolling", "promise", "tomorrow", "revival", "least", "attack", "season", "slump", "heat", "kind", "double", "problem", "pro", "tonight", "moves", "check", "strength", "soak", "stake", "aside", "field", "nice", "star", "surprise", "chart", "stay", "leave", "tackle", "why", "drive", "face"], "0": ["text", "cyprus", "orleans", "jay", "tusk", "ben", "austerity", "avon", "libya", "country", "typo", "israel", "bull", "atlanta", "ms", "sis", "boxing", "ethiopia", "forest", "johnson", "sa", "houston", "london", "broadway", "bowie", "lp", "stephen", "vancouver", "east", "read", "arab", "european", "society", "dutch", "soundtrack", "thread", "british", "whistler", "kendall", "cambridge", "sovereign", "tasmania", "population", "king", "isis", "playbill", "uk", "prosperity", "bruce", "land"], "3": ["son", "crate", "graves", "terror", "wedding", "condition", "priest", "suspect", "discovery", "hero", "homelessness", "police", "boy", "daughter", "trial", "pregnancy", "polka", "vehicle", "borders", "door", "beloved", "heart", "agent", "heard", "brake", "shooting", "safe", "office", "cage", "immortal", "pet", "jeep", "neighbor", "engagement", "friend", "murder", "homicide", "coward", "circus", "dog", "sleeper", "puppy", "friends", "request"], "2": ["gold", "yellow", "sleeve", "large", "item", "tent", "blue", "rings", "masking", "sapphire", "wall", "height", "belt", "diamond", "loft", "folding", "fleece", "roof", "brow", "balaclava", "pad", "inch", "pink", "signature", "shirt", "neck", "thermal", "carat", "mask", "hat", "halo", "stopper", "navy", "trench", "canvas", "flower", "red", "hull", "ring", "hood", "size", "camera", "fashion", "cover", "medium", "green", "leek", "original"], "4": ["booze", "milk", "cheeseburger", "drinking", "caramel", "bars", "apple", "watering", "checkout", "chocolate", "vodka", "delight", "flavor", "bread", "medicine", "truffle", "drink", "pub", "craving", "ate", "curry", "coupon", "ordering", "pie", "sauce", "potato"]}}