{"dozens": {"1": ["bomb", "radio", "bodybuilding", "religious", "northern", "mosque", "screening", "population", "woman", "appointment", "wedding", "cook", "school", "genealogy", "sleep", "national", "assembly", "visiting", "reconstruction", "international", "public", "explosion", "sorrow", "water", "county", "bathroom", "army", "visit", "maintenance", "dozens", "meeting", "shopping", "fire", "company", "gas", "search", "baby", "daughter", "car", "court", "travel", "government", "party", "rain", "abuse", "ethnic", "audit", "truck", "violator", "cold", "police", "photographer", "march", "civilian", "bid", "traffic", "bank", "lightning", "garage", "found", "people", "torch", "dead", "group", "home", "girl", "profit", "leak", "escort", "health", "cars", "central", "service", "retail", "south", "engagement", "vote", "city", "revival", "attack", "farming", "war", "north", "pastor", "wholesale", "bridge", "general", "door", "shooting", "income", "cleric", "football", "camp", "storm", "wounded", "resolution"], "0": ["going", "worth", "beat", "bad", "wish", "guy", "see", "are", "concern", "updating", "enough", "niche", "component", "job", "let", "change", "great", "experience", "whole", "point", "simple", "fitness", "working", "much", "tell", "more", "direction", "account", "room", "work", "while", "making", "trump", "give", "process", "high", "if", "things", "voicing", "running", "productivity", "purchase", "stress", "remember", "relief", "order", "help", "money", "dose", "thanks", "still", "rapid", "better", "save", "might", "then", "know", "success", "bent", "always", "break", "right", "deal", "lead", "looking", "core", "run", "power", "use", "free", "reason", "care", "training", "wrong", "place", "open", "support", "there", "system", "least", "fight", "wonderful", "way", "lot", "offer", "fundamentals", "part", "buying", "he", "matter", "future", "feeling", "motivation", "single", "no", "self", "majority", "role", "take", "plan", "individual", "drive", "time", "fact"], "3": ["month", "four", "honoring", "eve", "morning", "news", "last", "rose", "two", "mark", "today", "following", "history", "days", "reporting", "latest", "half", "year", "night", "birthday", "first", "season", "stories", "at", "daily"], "2": ["gold", "cheat", "text", "music", "iraqi", "black", "dell", "fan", "louis", "bag", "scanning", "art", "module", "detection", "computer", "design", "afghanistan", "israeli", "muslim", "ukraine", "libya", "pakistan", "via", "madness", "snowboard", "anti", "fake", "hitler", "belt", "turkey", "browse", "live", "dictator", "collaborator", "diamond", "cunt", "graphic", "den", "machine", "european", "designer", "fascist", "companion", "user", "st", "vintage", "london", "hell", "bowie", "denver", "arab", "january", "canada", "kiev", "christmas", "benjamin", "oh", "david", "clinton", "image", "sheet", "damn", "hillary", "link", "isis", "temp", "video", "russia", "fashion", "book", "evergreen", "picture", "germany", "america", "directory"]}}