{"evening": {"1": ["bomb", "gown", "chaos", "radio", "paranoid", "lake", "breast", "wedding", "hall", "gun", "steakhouse", "river", "flavor", "recording", "wreck", "gentleman", "funeral", "relaxation", "accident", "restaurant", "beacon", "workplace", "expression", "cancer", "walk", "county", "live", "music", "climax", "life", "flight", "worker", "chocolate", "baby", "circle", "charity", "bridesmaid", "car", "soul", "beautiful", "dress", "party", "comedy", "pizza", "wheel", "cocktail", "drink", "birthday", "drone", "bottle", "patio", "unemployment", "brain", "mayor", "happiness", "death", "cup", "sky", "alchemy", "boom", "food", "scene", "gift", "audience", "aide", "owner", "home", "girl", "mood", "factory", "moon", "health", "lecture", "pub", "care", "violence", "conversation", "copper", "bath", "homeless", "wages", "mercury", "housing", "valley", "spat", "north", "escort", "hut", "bachelor", "tree", "youth", "guilt", "store", "supervisor", "argument", "chat", "sunset", "dancing", "self", "flood", "book", "star", "diet", "studio", "storyline", "painting"], "0": ["fans", "countdown", "morning", "anniversary", "news", "cloud", "today", "wake", "winter", "travel", "date", "summer", "cold", "evening", "night", "week", "year", "noon", "ice", "days", "afternoon", "weather", "tomorrow", "tonight", "trip", "snow", "football"], "3": ["nevada", "thursday", "black", "folks", "lord", "michael", "manchester", "dis", "jesus", "genius", "version", "lea", "leeds", "bowie", "via", "tuesday", "sarah", "russell", "liverpool", "spain", "hayes", "mr", "stream", "december", "sir", "android", "sin", "louisville", "yorkshire", "isaac", "february", "netherlands", "january", "twitter", "crown", "saturday", "christmas", "hazel", "friday", "florida", "sod", "xx", "camden", "california", "butt", "king", "rad", "erie", "cream", "bruce", "america"], "2": ["saying", "felt", "much", "ruin", "program", "pretty", "dislike", "sent", "kind", "prime", "sleeve", "bad", "see", "enough", "international", "job", "great", "last", "let", "load", "fantastic", "point", "constant", "positive", "going", "flat", "champion", "talent", "work", "hope", "meet", "crazy", "trump", "awesome", "high", "good", "times", "par", "things", "amazing", "ball", "wrong", "guys", "cycle", "short", "muscle", "dream", "playing", "rest", "thanks", "speed", "better", "potential", "thump", "might", "then", "bid", "possible", "know", "world", "bit", "now", "wings", "found", "side", "making", "heavy", "back", "finish", "driving", "space", "open", "looking", "everything", "issue", "turning", "power", "formation", "post", "standby", "keep", "place", "first", "major", "feel", "number", "nothing", "carry", "drove", "miss", "little", "there", "wonderful", "way", "final", "listen", "serve", "part", "true", "he", "hire", "zero", "matter", "highlight", "happy", "need", "note", "take", "snapshot", "nice", "chance", "tackle", "deadline", "time", "decision", "joining"]}}