{"extra": {"1": ["code", "jason", "anglican", "text", "jay", "tweet", "dungeon", "please", "leo", "bible", "metaphor", "howard", "hudson", "henry", "seattle", "shit", "composition", "map", "portal", "zen", "web", "application", "lewis", "fin", "sears", "robert", "re", "midi", "universe", "quiz", "para", "ea", "atlantic", "kylie", "ana", "links", "intro", "graham", "mil", "alabama", "structure", "windows", "derrick", "adam", "xavier"], "0": ["saying", "ratio", "paranoid", "young", "going", "sitting", "pocket", "ones", "room", "prime", "die", "large", "relation", "past", "are", "odd", "access", "enough", "masking", "specialist", "grumble", "eye", "attention", "let", "boss", "swift", "great", "shift", "step", "pick", "extra", "use", "raise", "two", "much", "call", "more", "abundance", "look", "might", "work", "meet", "figure", "give", "slip", "worry", "if", "huge", "things", "fill", "tack", "stack", "stress", "maybe", "contact", "position", "six", "duke", "money", "thanks", "loading", "better", "save", "then", "couple", "dark", "know", "collect", "found", "hard", "try", "space", "looking", "cause", "whiff", "equivalent", "discount", "reason", "days", "turn", "place", "number", "three", "vote", "tomorrow", "guess", "there", "least", "fight", "serve", "buying", "he", "relative", "rush", "matter", "flex", "eyes", "hungry", "need", "lie", "take"], "3": ["foul", "mile", "scratch", "circle", "plate", "icing", "minute", "bar", "race", "team", "solo", "seat", "clock", "score", "kicker", "credits", "career", "touchdown", "winning", "throw", "possession", "trail", "wild", "anchor", "goal", "dove", "dream", "point", "bench", "kick", "march", "game", "grid", "half", "wings", "night", "luck", "tie", "crown", "hail", "run", "base", "teammate", "chapter", "yard", "afternoon", "spinning", "gig", "line", "double", "minutes", "tonight", "conversion", "field", "play", "championship", "knee"], "2": ["lace", "gold", "olive", "radio", "skin", "acne", "cheeseburger", "sugar", "black", "boyfriend", "bustle", "ticket", "gum", "ceasefire", "national", "acid", "alsatian", "blouse", "cooking", "fossil", "yogurt", "commercial", "water", "bachelor", "toothbrush", "guacamole", "community", "stiletto", "church", "vehicle", "pencil", "shopping", "chocolate", "minister", "baby", "tank", "lizard", "honey", "girlfriend", "species", "psychiatrist", "pint", "oil", "prosperity", "driver", "collection", "kit", "butter", "jean", "cold", "treatment", "hobby", "coffee", "material", "dryer", "baking", "wagon", "towel", "sequin", "authenticity", "girl", "jewelry", "formula", "knife", "cart", "craving", "shipping", "pollution", "origin", "cheese", "coupon", "relations", "delicious", "city", "authentic", "dynamite", "ivory", "hotel", "melanin", "toner", "cleaner", "coconut", "ginger", "film", "car", "yoga", "corporation", "bagel", "income", "holly", "mustard", "accidental", "buffalo", "sale", "salt"]}}