{"god_bless_america": {"1": ["liar", "charles", "sung", "dick", "black", "lord", "song", "jack", "words", "jacob", "clark", "ted", "download", "christian", "blue", "anthem", "please", "europe", "amen", "ignorance", "pea", "montreal", "radish", "reagan", "fake", "singing", "devil", "ph", "irving", "berlin", "smile", "word", "morgan", "fuck", "read", "sin", "sandwich", "elizabeth", "japan", "yes", "la", "sweet", "easter", "ya", "band", "greeting", "detroit", "bless", "allah", "god", "venezuela", "christmas", "eagle", "american", "cheese", "americans", "acne", "hey", "white", "jesus", "jordan", "butt", "grace", "mercy", "bucket", "planet", "ballad", "taylor", "israel", "ray", "rainbow", "green", "america", "don", "sun", "wow"], "0": ["sleep", "ticket", "him", "school", "she", "prayers", "national", "culture", "constitution", "nightmare", "state", "hero", "cab", "marines", "country", "drug", "soldier", "military", "family", "drunk", "trust", "life", "dropout", "phone", "daughter", "cash", "values", "history", "heart", "council", "information", "bullying", "birthday", "opinion", "president", "person", "jail", "order", "negligence", "food", "death", "campaign", "policy", "boom", "government", "nation", "bread", "gift", "university", "old", "people", "house", "election", "girl", "living", "chaos", "conservative", "health", "independence", "dirt", "faith", "sister", "freedom", "image", "vote", "wages", "city", "spending", "war", "north", "he", "college", "bridge", "prayer", "campus", "peace", "who", "plan", "coverage", "friends", "desert", "land", "wife", "flag", "mass"], "3": ["show", "follow", "finally", "stop", "celebrate", "eve", "morning", "race", "video", "are", "version", "closed", "screen", "wild", "picking", "strong", "swift", "change", "last", "bow", "games", "action", "via", "fashion", "three", "next", "live", "today", "challenge", "will", "making", "trump", "give", "high", "goal", "bowl", "plus", "course", "shape", "thanks", "airing", "rose", "winning", "kick", "game", "performance", "front", "reckoning", "lost", "night", "parade", "back", "alive", "year", "event", "lead", "finale", "turning", "stage", "face", "success", "keep", "turn", "place", "first", "two", "open", "tomorrow", "fight", "start", "forward", "delivery", "line", "trio", "tonight", "shooting", "take", "play", "star", "pool", "playing"], "2": ["help", "going", "hope", "see", "best", "we", "ability", "here", "let", "great", "whole", "simple", "everybody", "much", "must", "me", "work", "can", "fun", "beautiful", "thing", "things", "amazing", "may", "guys", "maybe", "well", "avenue", "fix", "better", "smart", "real", "good", "safe", "know", "always", "right", "looking", "reason", "think", "blessed", "everyone", "little", "there", "wonderful", "lot", "happy", "wish", "matter", "problem", "listen", "say", "need", "no", "you", "nothing", "proud"]}}