{"ready": {"1": ["sleep", "buddy", "tusk", "sycophancy", "brown", "jerk", "photography", "button", "cloudiness", "dip", "chicago", "bruno", "mum", "swansea", "body", "lee", "water", "police", "earthquake", "via", "madness", "county", "pod", "hovercraft", "faint", "damn", "toronto", "asheville", "baby", "spain", "wood", "wallet", "cam", "standby", "radiation", "vancouver", "shasta", "goner", "bale", "kit", "shirt", "codeine", "st", "nancy", "ambulance", "kelly", "thanks", "cold", "republican", "sky", "delhi", "newcastle", "bryan", "february", "january", "lucy", "found", "luck", "dead", "wednesday", "girl", "saturday", "jackson", "god", "caveman", "nepal", "daniel", "civilization", "vinyl", "oh", "jeep", "florida", "adrian", "bath", "delicious", "john", "head", "memphis", "info", "tree", "bed", "mary", "crystal", "russia", "palace", "snow", "illinois", "america", "wine", "salt"], "0": ["coach", "show", "session", "battle", "anticipation", "countdown", "beat", "school", "list", "eve", "morning", "race", "team", "release", "bill", "past", "edition", "video", "scrap", "version", "meet", "hours", "last", "action", "baseball", "semester", "conference", "visit", "two", "next", "today", "entrance", "heavyweight", "procedure", "court", "winter", "travel", "six", "party", "week", "premiere", "collection", "birthday", "adventure", "entry", "summer", "bowl", "midnight", "kickoff", "course", "group", "rose", "squad", "bye", "kick", "march", "break", "game", "victory", "night", "heist", "spring", "year", "home", "album", "re", "schedule", "training", "days", "dinner", "place", "road", "first", "wrap", "tomorrow", "start", "final", "baptism", "minutes", "voucher", "fashion", "partnership", "tonight", "newsletter", "book", "football", "audition", "weekend", "class", "daily"], "3": ["stock", "marketing", "market", "selling", "brand", "ad"], "2": ["hands", "corner", "everything", "going", "hope", "handle", "rise", "telling", "guy", "vision", "preserve", "peek", "frame", "sign", "intensity", "are", "pass", "close", "nothing", "boost", "public", "we", "infrastructure", "let", "strong", "come", "change", "wait", "great", "feeling", "step", "thinking", "learning", "use", "tread", "live", "much", "interest", "tell", "more", "hurry", "matter", "save", "work", "aim", "can", "making", "voice", "heart", "trump", "give", "process", "high", "importing", "bias", "ready", "if", "things", "sneak", "running", "guys", "contact", "left", "move", "discipline", "somewhere", "fix", "better", "might", "big", "know", "world", "tick", "right", "absolutely", "back", "beyond", "scale", "looking", "safety", "everybody", "who", "free", "thing", "commitment", "tackle", "open", "size", "little", "opportunity", "there", "fast", "offer", "nobody", "hear", "line", "he", "jump", "see", "prospect", "well", "mind", "life", "need", "lie", "mutual", "zero", "no", "self", "take", "sure", "services", "clear"]}}