{"time": {"1": ["influenza", "shot", "month", "four", "minute", "list", "morning", "national", "past", "review", "net", "leg", "last", "career", "games", "point", "period", "semester", "three", "next", "tense", "account", "budget", "history", "metropolitan", "sting", "days", "high", "middle", "stroke", "bowl", "delay", "yesterday", "date", "cycle", "short", "third", "rest", "halftime", "break", "game", "grid", "half", "weather", "side", "series", "energy", "back", "home", "re", "induction", "night", "stage", "training", "place", "promotion", "south", "first", "grade", "number", "two", "tomorrow", "spending", "weekend", "least", "start", "final", "head", "storm", "season", "volume", "second", "minutes", "year", "tonight", "single", "at", "zero", "time", "wake", "senior"], "0": ["shop", "radio", "music", "local", "song", "aurora", "samuel", "amazon", "fan", "words", "school", "reading", "democrat", "sleep", "art", "reference", "pulse", "video", "please", "champagne", "body", "water", "flies", "madness", "solitude", "anti", "fake", "hitler", "breath", "dictator", "life", "fire", "company", "search", "baby", "charity", "car", "mi", "air", "daft", "dad", "tan", "court", "till", "party", "birthday", "statue", "expression", "tho", "person", "jean", "violator", "bowie", "drunk", "royal", "blog", "son", "crying", "coffee", "read", "opera", "january", "heart", "people", "senate", "library", "brother", "milan", "cleveland", "girl", "mood", "god", "ice", "hill", "christmas", "cars", "scepter", "finland", "punk", "david", "drama", "snowboarding", "guard", "city", "sheet", "museum", "man", "manchester", "park", "he", "bed", "ur", "planet", "nightlife", "piece", "pro", "modality", "self", "snow", "nap", "book", "korean", "star", "symbol", "football", "friends", "room", "age", "humanitarian"], "3": ["show", "catch", "stop", "die", "sign", "download", "wear", "come", "change", "wait", "escape", "walk", "use", "stream", "live", "waste", "present", "give", "keep", "turn", "watch", "running", "move", "kill", "save", "march", "blowing", "free", "open", "dump", "listen", "rush", "take", "play", "stay", "don"], "2": ["relationships", "going", "pretty", "folks", "worth", "hope", "cool", "bad", "guy", "see", "are", "best", "enough", "impact", "we", "job", "let", "great", "feeling", "opinion", "whole", "patience", "laugh", "better", "eye", "much", "tell", "more", "look", "work", "fun", "making", "if", "things", "amazing", "well", "help", "money", "thanks", "aspect", "still", "perfect", "thinking", "feel", "might", "real", "big", "know", "now", "always", "works", "everyone", "hard", "looking", "reason", "wrong", "thing", "think", "right", "fast", "guess", "way", "damn", "part", "wish", "matter", "mind", "need", "thought", "no", "sure", "cause"]}}