{"timetable": {"1": ["staff", "re", "send", "stop", "closure", "try", "release", "sign", "are", "run", "waiting", "exercise", "complement", "meet", "change", "wait", "action", "walk", "standing", "use", "working", "next", "reduction", "call", "timetable", "work", "will", "making", "loop", "give", "high", "tab", "end", "check", "write", "may", "overall", "running", "short", "changes", "order", "latest", "feedback", "move", "rest", "shape", "thanks", "web", "fix", "help", "details", "return", "bid", "break", "front", "term", "back", "special", "looking", "turning", "fitness", "given", "free", "post", "training", "turn", "positive", "replacement", "major", "open", "start", "head", "statement", "offering", "padding", "line", "partnership", "single", "need", "take", "revision", "plan", "structure", "cover", "drive", "stick"], "0": ["saying", "liking", "felt", "fine", "ruin", "going", "pretty", "worth", "hope", "do", "means", "words", "bad", "stuff", "guy", "see", "best", "genius", "we", "let", "great", "whole", "guesstimate", "much", "tell", "might", "fun", "shame", "if", "thing", "things", "guys", "remember", "well", "thought", "money", "hell", "yes", "still", "perfect", "better", "real", "then", "read", "big", "know", "now", "bullshit", "laughing", "always", "mean", "em", "everyone", "absolutely", "god", "everything", "cause", "reason", "anything", "wrong", "think", "there", "lesson", "way", "listen", "nobody", "he", "wish", "matter", "maybe", "problem", "feeling", "argument", "shit", "no", "lately", "you", "nothing", "happening", "lot", "fact"], "3": ["downpour", "beat", "venue", "eve", "morning", "team", "calendar", "hours", "last", "sparring", "point", "two", "today", "hour", "straight", "times", "week", "spot", "birthday", "date", "game", "course", "weekly", "bout", "holiday", "earnest", "half", "spring", "year", "trophy", "days", "dinner", "expecting", "afternoon", "first", "tomorrow", "night", "least", "tonight", "at", "trip", "hangover", "clash", "weekend", "place", "time"], "2": ["queen", "avalanche", "sleep", "black", "screening", "woman", "school", "she", "bill", "disaster", "prayers", "college", "movie", "water", "trial", "family", "west", "life", "train", "adult", "baby", "town", "bin", "sleeping", "punctuality", "party", "student", "identity", "road", "office", "republican", "mail", "government", "traffic", "heart", "old", "people", "election", "home", "girl", "chaos", "lecture", "red", "football", "small", "care", "routes", "south", "city", "story", "ancient", "service", "festival", "fiction", "war", "bus", "bed", "passenger", "campus", "car", "mountain", "madwoman", "department", "who", "class", "professor", "barren"], "4": ["smash", "thursday", "matthew", "johnson", "st", "bowie", "sydney", "easter", "australia", "bang", "january", "chuck", "pacific", "christmas", "david", "hillary", "terry"]}}